setup.py
tick_ex_forex_next3/__init__.py
tick_ex_forex_next3/tick_ex_forex_next3.py
tick_ex_forex_next3.egg-info/PKG-INFO
tick_ex_forex_next3.egg-info/SOURCES.txt
tick_ex_forex_next3.egg-info/dependency_links.txt
tick_ex_forex_next3.egg-info/not-zip-safe
tick_ex_forex_next3.egg-info/top_level.txt