Metadata-Version: 1.0
Name: tick-ex-forex-next3
Version: 1.8
Summary: tick_ex_forex_next3
Home-page: UNKNOWN
Author: omid
Author-email: UNKNOWN
License: UNKNOWN
Platform: UNKNOWN
